MANIFEST.in
README.rst
pyproject.toml
setup.cfg
setup.py
docs/info.txt
maetl_report.egg-info/PKG-INFO
maetl_report.egg-info/SOURCES.txt
maetl_report.egg-info/dependency_links.txt
maetl_report.egg-info/requires.txt
maetl_report.egg-info/top_level.txt
report/__init__.py
report/admin.py
report/apps.py
report/forms.py
report/models.py
report/tests.py
report/urls.py
report/urls_administration.py
report/urls_development.py
report/urls_population.py
report/views.py
report/templates/administration/A1.html
report/templates/administration/A10.html
report/templates/administration/A11.html
report/templates/administration/A2.html
report/templates/administration/A3.html
report/templates/administration/A4.html
report/templates/administration/A5.html
report/templates/administration/A6.html
report/templates/administration/A7.html
report/templates/administration/PrintA1.html
report/templates/administration/PrintA10.html
report/templates/administration/PrintA11.html
report/templates/administration/PrintA2.html
report/templates/administration/PrintA3.html
report/templates/administration/PrintA4.html
report/templates/administration/PrintA5.html
report/templates/administration/PrintA6.html
report/templates/administration/PrintA7.html
report/templates/administration/dashboard.html
report/templates/development/dashboard.html
report/templates/development/print/activity.html
report/templates/development/print/project.html
report/templates/population_report/dashboard.html
report/templates/population_report/b1/reportjeral-b1-administrative.html
report/templates/population_report/b1/reportjeral-b1-aldeia.html
report/templates/population_report/b1/reportjeral-b1-print.html
report/templates/population_report/b1/reportjeral-b1-village.html
report/templates/population_report/b1/reportjeral-b1.html
report/templates/population_report/b4/reportjeral-b4-print.html
report/templates/population_report/b4/reportjeral-b4.html
report/templates/population_report/b4/reportjeralmunisipiu-b4-print.html
report/templates/population_report/b4/reportjeralpostu-b4-print.html
report/templates/population_report/b4/reportjeralsuku-b4-print.html
report/templates/report/dashboard.html
